compare_for_testing/__init__.py
compare_for_testing/compare.py
compare_for_testing/test/__init__.py
compare_for_testing/test/test_demo.py
compare_for_testing-1.2.1.dist-info/METADATA
compare_for_testing-1.2.1.dist-info/WHEEL
compare_for_testing-1.2.1.dist-info/top_level.txt
compare_for_testing-1.2.1.dist-info/RECORD
