Metadata-Version: 2.1
Name: compare-for-testing
Version: 1.2.1
Home-page: https://github.com/vaindante/compare_for_testing
Author: vaindante
Author-email: vaindante@gmail.ru
Classifier: Programming Language :: Python :: 3.6
Classifier: License :: OSI Approved :: MIT License
Classifier: Operating System :: OS Independent
